Detector de paridad/detector.vhd
library ieee;
use ieee.std_logic_1164.all;

--es un detector de paridad de 2 bits. Puede detectar paridad par e impar.
--par = 1 -> paridad par ; par = 0 -> paridad impar.
entity Detector is
  port(
    a, b, par : std_logic;
    paridad : out std_logic);
end;


architecture behave of Detector is
  --declaraciones
  begin
    paridad <= ( par and (not A) and B ) or ( par and A and (not B) ) or ( (not par) and (not A) and (not b) ) or ( (not par) and A and B );
end;

Detector de paridad/detector_tb.vhd
library ieee;
use ieee.std_logic_1164.all;

entity Simulator is
end entity;


architecture behave of Simulator is
  --Llamada a la entidad bajo testeo
  component Detector
    port(
      a, b, par : std_logic;
      paridad : out std_logic);
  end component;

  --Declaración de señales
  signal a, b, par, paridad: std_logic;
  
  begin
    uut : Detector port map(a, b, par, paridad);
      
      process
        begin
          --Paridad Impar
          par <= '0';
          a <= '0' ; b <= '0';
          wait for 10 ns;
          a <= '0' ; b <= '1';
          wait for 10 ns;
          a <= '1' ; b <= '0';
          wait for 10 ns;
          a <= '1' ; b <= '1';
          wait for 10 ns;

          --Paridad Par
          par <= '1';
          a <= '0' ; b <= '0';
          wait for 10 ns;
          a <= '0' ; b <= '1';
          wait for 10 ns;
          a <= '1' ; b <= '0';
          wait for 10 ns;
          a <= '1' ; b <= '1';
          wait for 10 ns;        
          wait;
        end process;
end architecture;

Detector de paridad/simulator.vcd
$date
  Fri Apr  8 12:18:38 2022
$end
$version
  GHDL v0
$end
$timescale
  1 fs
$end
$scope module standard $end
$upscope $end
$scope module std_logic_1164 $end
$upscope $end
$scope module simulator $end
$var reg 1 ! a $end
$var reg 1 " b $end
$var reg 1 # par $end
$var reg 1 $ paridad $end
$scope module uut $end
$var reg 1 % a $end
$var reg 1 & b $end
$var reg 1 ' par $end
$var reg 1 ( paridad $end
$upscope $end
$upscope $end
$enddefinitions $end
#0
0!
0"
0#
1$
0%
0&
0'
1(
#10000000
1"
0$
1&
0(
#20000000
1!
0"
1%
0&
#30000000
1"
1$
1&
1(
#40000000
0!
0"
1#
0$
0%
0&
1'
0(
#50000000
1"
1$
1&
1(
#60000000
1!
0"
1%
0&
#70000000
1"
0$
1&
0(
